pysetusver/__init__.py
pysetusver/pysetusver.py
pysetusver-2.0.0.dist-info/METADATA
pysetusver-2.0.0.dist-info/WHEEL
pysetusver-2.0.0.dist-info/top_level.txt
pysetusver-2.0.0.dist-info/RECORD
