Metadata-Version: 2.1
Name: pysetusver
Version: 2.0.0
Summary: letmeseesee
Home-page: UNKNOWN
Author: HANASE
Author-email: shenziqian66@163.com
License: UNKNOWN
Platform: UNKNOWN
Classifier: Programming Language :: Python :: 3
Classifier: License :: OSI Approved :: Apache Software License
Classifier: Operating System :: OS Independent
